pymedphys_labs/__init__.py
pymedphys_labs/_install_requires.py
pymedphys_labs/_version.py
pymedphys_labs/film/__init__.py
pymedphys_labs/film/align.py
pymedphys_labs/film/calibrate.py
pymedphys_labs/film/optical_density.py
pymedphys_labs/mattsobolewski/__init__.py
pymedphys_labs/mattsobolewski/wlutzfilesort.py
pymedphys_labs/paulking/__init__.py
pymedphys_labs/paulking/collequivalent.py
pymedphys_labs/paulking/devicesfilm.py
pymedphys_labs/paulking/devicessncprofiler.py
pymedphys_labs/paulking/narrow_png.py
pymedphys_labs/paulking/profile.py
pymedphys_labs/paulking/sinogram.py
pymedphys_labs/paulking/tempCodeRunnerFile.py
pymedphys_labs/paulking/tomo_sinogram_csv2pdf.py
pymedphys_labs/pedromartinez/__init__.py
pymedphys_labs/pedromartinez/qc-jaws.py
pymedphys_labs/tpscompare/__init__.py
pymedphys_labs/tpscompare/bulkcompare.py
pymedphys_labs/tpscompare/mephysto.py
pymedphys_labs/tpscompare/normalisation.py
pymedphys_labs-0.11.0.dist-info/LICENSE-AGPL-3.0-or-later
pymedphys_labs-0.11.0.dist-info/LICENSE-Apache-2.0
pymedphys_labs-0.11.0.dist-info/METADATA
pymedphys_labs-0.11.0.dist-info/WHEEL
pymedphys_labs-0.11.0.dist-info/top_level.txt
pymedphys_labs-0.11.0.dist-info/RECORD
