Metadata-Version: 2.1
Name: pymedphys-labs
Version: 0.11.0
Summary: UNKNOWN
Home-page: UNKNOWN
Author: PyMedPhys Contributors
Author-email: developers@pymedphys.com
License: AGPL-3.0-or-later
Platform: UNKNOWN
Classifier: Development Status :: 4 - Beta
Classifier: License :: OSI Approved :: GNU Affero General Public License v3 or later (AGPLv3+)
Classifier: Programming Language :: Python :: 3.7
Classifier: Topic :: Scientific/Engineering :: Medical Science Apps.
Classifier: Topic :: Scientific/Engineering :: Physics
Classifier: Intended Audience :: Science/Research
Classifier: Intended Audience :: Healthcare Industry
Requires-Python: >=3.7
Requires-Dist: Pillow
Requires-Dist: imageio
Requires-Dist: matplotlib
Requires-Dist: numpy (>=1.12)
Requires-Dist: pydicom
Requires-Dist: pymedphys-fileformats (<0.12.0,>=0.11.0)
Requires-Dist: pymedphys-utilities (<0.12.0,>=0.11.0)
Requires-Dist: scikit-image
Requires-Dist: scipy
Requires-Dist: tqdm
Provides-Extra: test
Requires-Dist: pytest ; extra == 'test'
Requires-Dist: deepdiff ; extra == 'test'
